BirdSTEM/__init__.py
BirdSTEM/test.py
BirdSTEM/dataset/__init__.py
BirdSTEM/dataset/generate_random_samples.py
BirdSTEM/dataset/get_test_x_names.py
BirdSTEM/dataset/load_test_data.py
BirdSTEM/dataset/request_env_data.py
BirdSTEM/model/AdaSTEM.py
BirdSTEM/model/Hurdle.py
BirdSTEM/model/__init__.py
BirdSTEM/model/dummy_model.py
BirdSTEM/model/test.py
BirdSTEM/utils/__init__.py
BirdSTEM/utils/generate_soft_colors.py
BirdSTEM/utils/plot_gif.py
BirdSTEM/utils/quadtree.py
BirdSTEM-0.0.3.dist-info/LICENSE
BirdSTEM-0.0.3.dist-info/METADATA
BirdSTEM-0.0.3.dist-info/WHEEL
BirdSTEM-0.0.3.dist-info/top_level.txt
BirdSTEM-0.0.3.dist-info/RECORD
