Metadata-Version: 2.1
Name: BirdSTEM
Version: 0.0.3
Summary: AdaSTEM model for daily abundance estimation using eBird citizen science data
Author: Yangkang Chen
Author-email: chenyangkang24@outlook.com
Keywords: python,ebird,spatial-temporal model,citizen science,spatial temporal exploratory model,STEM,AdaSTEM,abundance,phenology
Classifier: Development Status :: 1 - Planning
Classifier: Programming Language :: Python :: 3
Classifier: Operating System :: Unix
Classifier: Operating System :: MacOS :: MacOS X
Classifier: Operating System :: Microsoft :: Windows
License-File: LICENSE
